sib/__init__.py
sib/_version.py
sib/clustering_utils.py
sib/sib_main.py
sib/sib_optimizer_c.py
sib/sib_optimizer_p.py
sib/c_package/__init__.py
sib/c_package/c_sib_optimizer.cp311-win_amd64.pyd
sib/c_package/c_sib_optimizer.cpp
sib/c_package/c_sib_optimizer.pxd
sib/c_package/c_sib_optimizer.pyx
sib/c_package/sib_optimizer.cpp
sib/c_package/sib_optimizer.h
sib_clustering-0.2.7.dist-info/licenses/LICENSE
sib_clustering-0.2.7.dist-info/METADATA
sib_clustering-0.2.7.dist-info/WHEEL
sib_clustering-0.2.7.dist-info/top_level.txt
sib_clustering-0.2.7.dist-info/RECORD
